{
  "driver": "C#",
  "repository": "https://github.com/mongodb/mongo-csharp-driver",
  "versions": [
    {
      "version": "3.4.2",
      "releaseDate": "2025-07-25"
    },
    {
      "version": "3.4.1",
      "releaseDate": "2025-07-16"
    },
    {
      "version": "3.4.0",
      "releaseDate": "2025-05-01"
    },
    {
      "version": "3.3.0",
      "releaseDate": "2025-03-28"
    },
    {
      "version": "3.2.1",
      "releaseDate": "2025-02-20"
    },
    {
      "version": "3.2.0",
      "releaseDate": "2025-02-12"
    },
    {
      "version": "3.1.0",
      "releaseDate": "2024-12-05"
    },
    {
      "version": "3.0.0",
      "releaseDate": "2024-10-16"
    },
    {
      "version": "2.30.0",
      "releaseDate": "2024-10-16"
    },
    {
      "version": "2.29.0",
      "releaseDate": "2024-09-18"
    },
    {
      "version": "2.28.0",
      "releaseDate": "2024-07-23"
    },
    {
      "version": "2.27.0",
      "releaseDate": "2024-06-28"
    },
    {
      "version": "2.26.0",
      "releaseDate": "2024-06-12"
    },
    {
      "version": "2.25.0",
      "releaseDate": "2024-04-12"
    },
    {
      "version": "2.24.0",
      "releaseDate": "2024-02-21"
    },
    {
      "version": "2.23.2",
      "releaseDate": "2024-02-20"
    },
    {
      "version": "2.23.1",
      "releaseDate": "2023-12-15"
    },
    {
      "version": "2.23.0",
      "releaseDate": "2023-12-12"
    },
    {
      "version": "2.22.0",
      "releaseDate": "2023-10-09"
    },
    {
      "version": "2.21.0",
      "releaseDate": "2023-08-10"
    },
    {
      "version": "2.20.0",
      "releaseDate": "2023-06-21"
    },
    {
      "version": "2.19.2",
      "releaseDate": "2023-05-25"
    },
    {
      "version": "2.19.1",
      "releaseDate": "2023-03-27"
    },
    {
      "version": "2.19.0",
      "releaseDate": "2023-01-27"
    },
    {
      "version": "2.18.0",
      "releaseDate": "2022-10-14"
    },
    {
      "version": "2.17.1",
      "releaseDate": "2022-07-30"
    },
    {
      "version": "2.17.0",
      "releaseDate": "2022-07-18"
    },
    {
      "version": "2.16.1",
      "releaseDate": "2022-06-21"
    },
    {
      "version": "2.16.0",
      "releaseDate": "2022-06-06"
    },
    {
      "version": "2.15.1",
      "releaseDate": "2022-05-09"
    },
    {
      "version": "2.15.0",
      "releaseDate": "2022-03-09"
    },
    {
      "version": "2.14.1",
      "releaseDate": "2021-12-02"
    },
    {
      "version": "2.14.0",
      "releaseDate": "2021-11-24"
    },
    {
      "version": "2.13.3",
      "releaseDate": "2021-11-23"
    },
    {
      "version": "2.13.2",
      "releaseDate": "2021-10-06"
    },
    {
      "version": "2.13.1",
      "releaseDate": "2021-08-04"
    },
    {
      "version": "2.13.0",
      "releaseDate": "2021-07-13"
    },
    {
      "version": "2.12.5",
      "releaseDate": "2021-11-23"
    },
    {
      "version": "2.12.4",
      "releaseDate": "2021-06-04"
    },
    {
      "version": "2.12.3",
      "releaseDate": "2021-05-04"
    },
    {
      "version": "2.12.2",
      "releaseDate": "2021-04-07"
    },
    {
      "version": "2.12.1",
      "releaseDate": "2021-03-23"
    },
    {
      "version": "2.12.0",
      "releaseDate": "2021-03-03"
    },
    {
      "version": "2.11.6",
      "releaseDate": "2021-01-20"
    },
    {
      "version": "2.11.5",
      "releaseDate": "2020-12-02"
    },
    {
      "version": "2.11.4",
      "releaseDate": "2020-11-04"
    },
    {
      "version": "2.11.3",
      "releaseDate": "2020-10-15"
    },
    {
      "version": "2.11.2",
      "releaseDate": "2020-09-10"
    },
    {
      "version": "2.11.1",
      "releaseDate": "2020-08-25"
    },
    {
      "version": "2.11.0",
      "releaseDate": "2020-07-30"
    },
    {
      "version": "2.10.4",
      "releaseDate": "2020-05-05"
    },
    {
      "version": "2.10.3",
      "releaseDate": "2020-04-07"
    },
    {
      "version": "2.10.2",
      "releaseDate": "2020-02-14"
    },
    {
      "version": "2.10.1",
      "releaseDate": "2020-01-15"
    },
    {
      "version": "2.10.0",
      "releaseDate": "2019-12-10"
    },
    {
      "version": "2.10.0-beta1",
      "releaseDate": "2019-10-02"
    },
    {
      "version": "2.9.3",
      "releaseDate": "2019-11-08"
    },
    {
      "version": "2.9.2",
      "releaseDate": "2019-09-30"
    },
    {
      "version": "2.9.1",
      "releaseDate": "2019-08-21"
    },
    {
      "version": "2.9.0",
      "releaseDate": "2019-08-15"
    },
    {
      "version": "2.8.1",
      "releaseDate": "2019-05-15"
    },
    {
      "version": "2.8.0",
      "releaseDate": "2019-03-13"
    },
    {
      "version": "2.7.3",
      "releaseDate": "2019-01-24"
    },
    {
      "version": "2.7.2",
      "releaseDate": "2018-11-10"
    },
    {
      "version": "2.7.1",
      "releaseDate": "2018-11-08"
    },
    {
      "version": "2.7.0",
      "releaseDate": "2018-06-27"
    },
    {
      "version": "2.6.1",
      "releaseDate": "2018-05-17"
    },
    {
      "version": "2.6.0",
      "releaseDate": "2018-04-24"
    },
    {
      "version": "2.5.1",
      "releaseDate": "2018-04-19"
    },
    {
      "version": "2.5.0",
      "releaseDate": "2017-12-12"
    },
    {
      "version": "2.4.4",
      "releaseDate": "2017-06-08"
    },
    {
      "version": "2.4.3",
      "releaseDate": "2017-03-09"
    },
    {
      "version": "2.4.2",
      "releaseDate": "2017-02-02"
    },
    {
      "version": "2.4.1",
      "releaseDate": "2017-01-04"
    },
    {
      "version": "2.4.0",
      "releaseDate": "2016-11-29"
    },
    {
      "version": "2.3.0",
      "releaseDate": "2016-09-23"
    },
    {
      "version": "2.2.4",
      "releaseDate": "2016-05-18"
    },
    {
      "version": "2.2.3",
      "releaseDate": "2016-02-02"
    },
    {
      "version": "2.2.2",
      "releaseDate": "2016-01-15"
    },
    {
      "version": "2.2.1",
      "releaseDate": "2016-01-08"
    },
    {
      "version": "2.2.0",
      "releaseDate": "2015-12-07"
    },
    {
      "version": "2.1.1",
      "releaseDate": "2015-11-11"
    },
    {
      "version": "2.1.0",
      "releaseDate": "2015-10-19"
    },
    {
      "version": "2.0.2",
      "releaseDate": "2015-11-11"
    },
    {
      "version": "2.0.1",
      "releaseDate": "2015-06-08"
    },
    {
      "version": "2.0.0",
      "releaseDate": "2015-04-02"
    },
    {
      "version": "1.11.0",
      "releaseDate": "2015-12-09"
    },
    {
      "version": "1.10.1",
      "releaseDate": "2015-08-12"
    },
    {
      "version": "1.10.0",
      "releaseDate": "2015-01-29"
    },
    {
      "version": "1.9.2",
      "releaseDate": "2014-06-30"
    },
    {
      "version": "1.9.1",
      "releaseDate": "2014-05-15"
    },
    {
      "version": "1.9.0",
      "releaseDate": "2014-04-03"
    },
    {
      "version": "1.8.3.9",
      "releaseDate": "2013-09-30"
    },
    {
      "version": "1.8.2.34",
      "releaseDate": "2013-08-07"
    },
    {
      "version": "1.8.1.20",
      "releaseDate": "2013-08-07"
    },
    {
      "version": "1.8.0.124",
      "releaseDate": "2013-08-07"
    },
    {
      "version": "1.7.1.4791",
      "releaseDate": "2013-08-07"
    },
    {
      "version": "1.7.0.4714",
      "releaseDate": "2013-08-07"
    },
    {
      "version": "1.6.1.4678",
      "releaseDate": "2013-08-07"
    },
    {
      "version": "1.6.0.4624",
      "releaseDate": "2013-08-07"
    }
  ]
}
